japanese_address/__init__.py
japanese_address/dataloader.py
japanese_address/data/__init__.py
japanese_address/data/cities.py
japanese_address/data/prefectures.py
japanese_address/data/towns.py
japanese_address/data/wards.py
japanese_address-0.2.dist-info/LICENSE
japanese_address-0.2.dist-info/METADATA
japanese_address-0.2.dist-info/WHEEL
japanese_address-0.2.dist-info/top_level.txt
japanese_address-0.2.dist-info/RECORD
