Metadata-Version: 2.1
Name: japanese-address
Version: 0.2
Summary: Japanese address parser
Home-page: https://github.com/kalessin/japanese-address
Author: Martin Olveyra
Author-email: molveyra@gmail.com
License: BSD
Classifier: Development Status :: 4 - Beta
Classifier: Intended Audience :: Developers
Classifier: License :: OSI Approved :: BSD License
Classifier: Operating System :: OS Independent
Classifier: Programming Language :: Python :: 3
License-File: LICENSE
Requires-Dist: parsel
